ProtocolDataUnits/__init__.py
ProtocolDataUnits/cli.py
ProtocolDataUnits/pdu.py
ProtocolDataUnits/examples/pdu_examples.py
protocoldataunits-1.0.3.dist-info/licenses/LICENSE
protocoldataunits-1.0.3.dist-info/METADATA
protocoldataunits-1.0.3.dist-info/WHEEL
protocoldataunits-1.0.3.dist-info/entry_points.txt
protocoldataunits-1.0.3.dist-info/top_level.txt
protocoldataunits-1.0.3.dist-info/RECORD
