Metadata-Version: 2.4
Name: ProtocolDataUnits
Version: 1.0.3
Summary: A Python toolset for encoding and decoding Protocol Data Units (PDUs)
Author-email: Jay Patel <patel.jay@dal.ca>, Mandar Chitre <mandar@nus.edu.sg>
License-Expression: MIT
Keywords: pdu,binary,protocol,serialization,modem,communication
Classifier: Programming Language :: Python :: 3
Classifier: Operating System :: OS Independent
Requires-Python: >=3.8
License-File: LICENSE
Requires-Dist: loguru
Dynamic: license-file
